{
  "type": "normal",
  "rawDescription": "【后院，昼】",
  "location": "后院",
  "timeOfDay": "昼",
  "performances": [
    { "type": "action", "description": "掌柜，老白进后院" },
    {
      "type": "dialog",
      "speaker": "佟湘玉",
      "performances": [
        {
          "type": "line",
          "line": "这才来了几天就学会赖床了，水也不烧，地也不扫，床也不叠。"
        }
      ]
    },
    {
      "type": "dialog",
      "speaker": "莫小贝",
      "performances": [{ "type": "line", "line": "没起床怎么叠被子呀！" }]
    },
    {
      "type": "dialog",
      "speaker": "佟湘玉",
      "performances": [
        { "type": "line", "line": "那是她的事儿" },
        { "type": "speaker-action", "description": "指小贝" },
        { "type": "line", "line": "去把她叫起来！" }
      ]
    },
    { "type": "action", "description": "小贝去屋里" },
    {
      "type": "dialog",
      "speaker": "莫小贝",
      "performances": [
        {
          "type": "line",
          "line": "哎，小郭姐姐，赶紧起，赶紧起！白大哥带着我嫂子杀过来啦！"
        }
      ]
    },
    {
      "type": "dialog",
      "speaker": "郭芙蓉",
      "performances": [
        { "type": "speaker-action", "description": "眯着眼睛，不愿起" },
        { "type": "line", "line": "来就来呗，有本事让他以一指点死我算啦！" }
      ]
    }
  ]
}
